setup.py
udacity_distributions_samuel_k/Binomialdistribution.py
udacity_distributions_samuel_k/Gaussiandistribution.py
udacity_distributions_samuel_k/Generaldistribution.py
udacity_distributions_samuel_k/__init__.py
udacity_distributions_samuel_k.egg-info/PKG-INFO
udacity_distributions_samuel_k.egg-info/SOURCES.txt
udacity_distributions_samuel_k.egg-info/dependency_links.txt
udacity_distributions_samuel_k.egg-info/not-zip-safe
udacity_distributions_samuel_k.egg-info/top_level.txt