Metadata-Version: 1.0
Name: udacity-distributions-samuel-k
Version: 0.1
Summary: Gaussian distributions
Home-page: UNKNOWN
Author: samuel.k
Author-email: samkura47@gmail.com
License: UNKNOWN
Platform: UNKNOWN
